{
  "config": {
    "cache_size_kb": 32,
    "block_sizes_bytes": [
      64,
      128,
      256
    ],
    "associativities": [
      1,
      2,
      4,
      8
    ],
    "replacement_policy": "LRU",
    "address_space_bits": 32,
    "output": {
      "output_dir": "results/matrix_mul_ikj",
      "csv_name": "cache_results.csv",
      "json_name": "cache_results.json",
      "summary_name": "summary.txt",
      "plot_hit_vs_block": "plot_block_vs_hit_rate.png",
      "plot_miss_vs_block": "plot_block_vs_miss_rate.png",
      "plot_hit_vs_assoc": "plot_assoc_vs_hit_rate.png",
      "plot_miss_vs_assoc": "plot_assoc_vs_miss_rate.png",
      "bar_hit_vs_block": "bar_block_vs_hit_rate.png",
      "bar_miss_vs_block": "bar_block_vs_miss_rate.png",
      "bar_hit_vs_assoc": "bar_assoc_vs_hit_rate.png",
      "bar_miss_vs_assoc": "bar_assoc_vs_miss_rate.png"
    },
    "engine": "gem5",
    "gem5": {
      "gem5_config_script": "scripts/gem5_cache_sweep.py",
      "benchmark_binary": "benchmarks/bin/matrix_mul",
      "gem5_binary": "../gem5/build/X86/gem5.opt",
      "benchmark_args": "128 ikj",
      "workload_name": "matrix_mul_ikj",
      "cpu_type": "TimingSimpleCPU",
      "mem_size": "2GB",
      "max_ticks": 1000000000,
      "stats_hits_key": "",
      "stats_misses_key": "",
      "output_subdir": "gem5_runs_matrix_mul_ikj",
      "resolved_gem5_binary": "../gem5/build/X86/gem5.opt"
    },
    "elapsed_seconds": 0.020376549000047817,
    "failed_runs": [],
    "completed_runs": 12,
    "total_runs": 12,
    "failed_count": 0
  },
  "results": [
    {
      "cache_size_kb": 32,
      "block_size_kb": 64,
      "block_size_bytes": 64,
      "associativity": 1,
      "replacement_policy": "LRU",
      "workload_name": "matrix_mul_ikj",
      "runtime_seconds": 0.0,
      "status": "success",
      "failure_reason": "",
      "notes": "Source: gem5 stats.txt ; status=success ; Run dir: results/matrix_mul_ikj/gem5_runs_matrix_mul_ikj/b64B_a1 ; hit_key_override=auto ; miss_key_override=auto ; Reused existing stats.txt (resume mode)",
      "total_accesses": 33938114,
      "hits": 32181243,
      "misses": 1756871,
      "hit_rate": 0.9482330986335894,
      "miss_rate": 0.051766901366410635
    },
    {
      "cache_size_kb": 32,
      "block_size_kb": 64,
      "block_size_bytes": 64,
      "associativity": 2,
      "replacement_policy": "LRU",
      "workload_name": "matrix_mul_ikj",
      "runtime_seconds": 0.0,
      "status": "success",
      "failure_reason": "",
      "notes": "Source: gem5 stats.txt ; status=success ; Run dir: results/matrix_mul_ikj/gem5_runs_matrix_mul_ikj/b64B_a2 ; hit_key_override=auto ; miss_key_override=auto ; Reused existing stats.txt (resume mode)",
      "total_accesses": 33938114,
      "hits": 32846602,
      "misses": 1091512,
      "hit_rate": 0.9678381656682513,
      "miss_rate": 0.032161834331748664
    },
    {
      "cache_size_kb": 32,
      "block_size_kb": 64,
      "block_size_bytes": 64,
      "associativity": 4,
      "replacement_policy": "LRU",
      "workload_name": "matrix_mul_ikj",
      "runtime_seconds": 0.0,
      "status": "success",
      "failure_reason": "",
      "notes": "Source: gem5 stats.txt ; status=success ; Run dir: results/matrix_mul_ikj/gem5_runs_matrix_mul_ikj/b64B_a4 ; hit_key_override=auto ; miss_key_override=auto ; Reused existing stats.txt (resume mode)",
      "total_accesses": 33938114,
      "hits": 32862952,
      "misses": 1075162,
      "hit_rate": 0.9683199249080252,
      "miss_rate": 0.03168007509197476
    },
    {
      "cache_size_kb": 32,
      "block_size_kb": 64,
      "block_size_bytes": 64,
      "associativity": 8,
      "replacement_policy": "LRU",
      "workload_name": "matrix_mul_ikj",
      "runtime_seconds": 0.0,
      "status": "success",
      "failure_reason": "",
      "notes": "Source: gem5 stats.txt ; status=success ; Run dir: results/matrix_mul_ikj/gem5_runs_matrix_mul_ikj/b64B_a8 ; hit_key_override=auto ; miss_key_override=auto ; Reused existing stats.txt (resume mode)",
      "total_accesses": 33938114,
      "hits": 32862993,
      "misses": 1075121,
      "hit_rate": 0.9683211329892993,
      "miss_rate": 0.03167886701070071
    },
    {
      "cache_size_kb": 32,
      "block_size_kb": 128,
      "block_size_bytes": 128,
      "associativity": 1,
      "replacement_policy": "LRU",
      "workload_name": "matrix_mul_ikj",
      "runtime_seconds": 0.0,
      "status": "success",
      "failure_reason": "",
      "notes": "Source: gem5 stats.txt ; status=success ; Run dir: results/matrix_mul_ikj/gem5_runs_matrix_mul_ikj/b128B_a1 ; hit_key_override=auto ; miss_key_override=auto ; Reused existing stats.txt (resume mode)",
      "total_accesses": 33938106,
      "hits": 32623746,
      "misses": 1314360,
      "hit_rate": 0.9612718517645032,
      "miss_rate": 0.0387281482354967
    },
    {
      "cache_size_kb": 32,
      "block_size_kb": 128,
      "block_size_bytes": 128,
      "associativity": 2,
      "replacement_policy": "LRU",
      "workload_name": "matrix_mul_ikj",
      "runtime_seconds": 0.0,
      "status": "success",
      "failure_reason": "",
      "notes": "Source: gem5 stats.txt ; status=success ; Run dir: results/matrix_mul_ikj/gem5_runs_matrix_mul_ikj/b128B_a2 ; hit_key_override=auto ; miss_key_override=auto ; Reused existing stats.txt (resume mode)",
      "total_accesses": 33938106,
      "hits": 33372030,
      "misses": 566076,
      "hit_rate": 0.9833203420367654,
      "miss_rate": 0.0166796579632346
    },
    {
      "cache_size_kb": 32,
      "block_size_kb": 128,
      "block_size_bytes": 128,
      "associativity": 4,
      "replacement_policy": "LRU",
      "workload_name": "matrix_mul_ikj",
      "runtime_seconds": 0.0,
      "status": "success",
      "failure_reason": "",
      "notes": "Source: gem5 stats.txt ; status=success ; Run dir: results/matrix_mul_ikj/gem5_runs_matrix_mul_ikj/b128B_a4 ; hit_key_override=auto ; miss_key_override=auto ; Reused existing stats.txt (resume mode)",
      "total_accesses": 33938106,
      "hits": 33399550,
      "misses": 538556,
      "hit_rate": 0.9841312299513709,
      "miss_rate": 0.015868770048629112
    },
    {
      "cache_size_kb": 32,
      "block_size_kb": 128,
      "block_size_bytes": 128,
      "associativity": 8,
      "replacement_policy": "LRU",
      "workload_name": "matrix_mul_ikj",
      "runtime_seconds": 0.0,
      "status": "success",
      "failure_reason": "",
      "notes": "Source: gem5 stats.txt ; status=success ; Run dir: results/matrix_mul_ikj/gem5_runs_matrix_mul_ikj/b128B_a8 ; hit_key_override=auto ; miss_key_override=auto ; Reused existing stats.txt (resume mode)",
      "total_accesses": 33938106,
      "hits": 33399603,
      "misses": 538503,
      "hit_rate": 0.9841327916177762,
      "miss_rate": 0.015867208382223805
    },
    {
      "cache_size_kb": 32,
      "block_size_kb": 256,
      "block_size_bytes": 256,
      "associativity": 2,
      "replacement_policy": "LRU",
      "workload_name": "matrix_mul_ikj",
      "runtime_seconds": 0.0,
      "status": "success",
      "failure_reason": "",
      "notes": "Source: gem5 stats.txt ; status=success ; Run dir: results/matrix_mul_ikj/gem5_runs_matrix_mul_ikj/b256B_a2 ; hit_key_override=auto ; miss_key_override=auto ; Reused existing stats.txt (resume mode)",
      "total_accesses": 33938105,
      "hits": 33623123,
      "misses": 314982,
      "hit_rate": 0.9907189278835692,
      "miss_rate": 0.00928107211643078
    },
    {
      "cache_size_kb": 32,
      "block_size_kb": 256,
      "block_size_bytes": 256,
      "associativity": 1,
      "replacement_policy": "LRU",
      "workload_name": "matrix_mul_ikj",
      "runtime_seconds": 0.0,
      "status": "success",
      "failure_reason": "",
      "notes": "Source: gem5 stats.txt ; status=success ; Run dir: results/matrix_mul_ikj/gem5_runs_matrix_mul_ikj/b256B_a1 ; hit_key_override=auto ; miss_key_override=auto ; Reused existing stats.txt (resume mode)",
      "total_accesses": 33938105,
      "hits": 32753542,
      "misses": 1184563,
      "hit_rate": 0.9650963717626544,
      "miss_rate": 0.0349036282373456
    },
    {
      "cache_size_kb": 32,
      "block_size_kb": 256,
      "block_size_bytes": 256,
      "associativity": 8,
      "replacement_policy": "LRU",
      "workload_name": "matrix_mul_ikj",
      "runtime_seconds": 0.0,
      "status": "success",
      "failure_reason": "",
      "notes": "Source: gem5 stats.txt ; status=success ; Run dir: results/matrix_mul_ikj/gem5_runs_matrix_mul_ikj/b256B_a8 ; hit_key_override=auto ; miss_key_override=auto ; Reused existing stats.txt (resume mode)",
      "total_accesses": 33938105,
      "hits": 33668189,
      "misses": 269916,
      "hit_rate": 0.9920468158136702,
      "miss_rate": 0.00795318418632979
    },
    {
      "cache_size_kb": 32,
      "block_size_kb": 256,
      "block_size_bytes": 256,
      "associativity": 4,
      "replacement_policy": "LRU",
      "workload_name": "matrix_mul_ikj",
      "runtime_seconds": 0.0,
      "status": "success",
      "failure_reason": "",
      "notes": "Source: gem5 stats.txt ; status=success ; Run dir: results/matrix_mul_ikj/gem5_runs_matrix_mul_ikj/b256B_a4 ; hit_key_override=auto ; miss_key_override=auto ; Reused existing stats.txt (resume mode)",
      "total_accesses": 33938105,
      "hits": 33668133,
      "misses": 269972,
      "hit_rate": 0.9920451657510047,
      "miss_rate": 0.007954834248995341
    }
  ]
}